sphinx_automagicdoc/__init__.py
sphinx_automagicdoc/entrypoint.py
sphinx_automagicdoc/mock.py
sphinx_automagicdoc/mock_filesystem.py
sphinx_automagicdoc/model.py
sphinx_automagicdoc/module_scanner.py
sphinx_automagicdoc/rst_preparation.py
sphinx_automagicdoc/util.py
sphinx_automagicdoc-0.0.2.dist-info/LICENSE
sphinx_automagicdoc-0.0.2.dist-info/WHEEL
sphinx_automagicdoc-0.0.2.dist-info/METADATA
sphinx_automagicdoc-0.0.2.dist-info/RECORD
