Metadata-Version: 2.1
Name: sphinx-automagicdoc
Version: 0.0.2
Summary: A plugin to automagically create autodoc-based API documentation files on the fly
Author-email: Christian Sachs <sachs.christian@gmail.com>
Requires-Dist: sphinx
Requires-Dist: Jinja2
Requires-Dist: black ; extra == "check"
Requires-Dist: isort ; extra == "check"
Requires-Dist: pyproject-flake8 ; extra == "check"
Requires-Dist: pylint ; extra == "check"
Requires-Dist: mypy ; extra == "check"
Requires-Dist: types-docutils ; extra == "check"
Requires-Dist: sphinx ; extra == "doc"
Requires-Dist: myst-parser ; extra == "doc"
Requires-Dist: sphinx-autopyproject ; extra == "doc"
Requires-Dist: sphinx-rtd-theme ; extra == "doc"
Project-URL: Home, https://github.com/csachs/sphinx-automagicdoc
Provides-Extra: check
Provides-Extra: doc
